tests/__init__.py
tests/add_1_to_a.py
tests/test_command_line.py
tests/test_data_surgery.py
tests/test_find.py
tests/test_format.py
tests/test_imports.py
tests/test_insert_replace.py
tests/test_multikernel.py
tests/test_python3.py
tests/test_sagemath.py
tests/test_sagemath_integration.py
tests/test_shuffle.py
tests/test_simplekernel.py
texsurgery/__init__.py
texsurgery/command_line.py
texsurgery/simplekernel.py
texsurgery/texsurgery.py
texsurgery-0.6.3.dist-info/LICENSE
texsurgery-0.6.3.dist-info/METADATA
texsurgery-0.6.3.dist-info/WHEEL
texsurgery-0.6.3.dist-info/entry_points.txt
texsurgery-0.6.3.dist-info/top_level.txt
texsurgery-0.6.3.dist-info/RECORD
