Metadata-Version: 2.1
Name: texsurgery
Version: 0.6.3
Summary: Replace some commands and environments within a TeX document by evaluating code inside a jupyter kernel
Home-page: https://framagit.org/pang/texsurgery
Author: Pablo Angulo, Juan Viu Sos, Miguel Angel Marco Buzunariz
Author-email: pablo.angulo@upm.es
License: UNKNOWN
Platform: UNKNOWN
Classifier: Programming Language :: Python :: 3
Classifier: License :: OSI Approved :: MIT License
Classifier: Operating System :: OS Independent
Requires-Python: >=3.6
Requires-Dist: jupyter-client
